setup.py
pushover/__init__.py
pushover/pushover.py
pushover_python.egg-info/PKG-INFO
pushover_python.egg-info/SOURCES.txt
pushover_python.egg-info/dependency_links.txt
pushover_python.egg-info/not-zip-safe
pushover_python.egg-info/top_level.txt