Metadata-Version: 1.1
Name: pushover-python
Version: 0.1
Summary: pushover simple api python implement
Home-page: https://github.com/toloy/pushover-python
Author: toloy
Author-email: ccoder64@hotmail.com
License: UNKNOWN
Keywords: pushover,pushover-python
Platform: UNKNOWN
Classifier: License :: OSI Approved :: MIT License
Classifier: Programming Language :: Python
Classifier: Intended Audience :: Developers
Classifier: Operating System :: OS Independent
